simple_error_log/__info__.py
simple_error_log/__init__.py
simple_error_log/error.py
simple_error_log/error_location.py
simple_error_log/errors.py
simple_error_log-0.7.0.dist-info/licenses/LICENSE
simple_error_log-0.7.0.dist-info/METADATA
simple_error_log-0.7.0.dist-info/WHEEL
simple_error_log-0.7.0.dist-info/top_level.txt
simple_error_log-0.7.0.dist-info/RECORD
